saini/__init__.py
saini/__main__.py
saini/analyzer.py
saini/cli.py
saini/config.py
saini/dashboard.py
saini/idle_detection.py
saini/pomodoro.py
saini/reports.py
saini/tracker.py
saini/tree.py
saini/utils.py
saini-1.0.5.dist-info/licenses/LICENSE
saini-1.0.5.dist-info/METADATA
saini-1.0.5.dist-info/WHEEL
saini-1.0.5.dist-info/entry_points.txt
saini-1.0.5.dist-info/top_level.txt
saini-1.0.5.dist-info/RECORD
