Metadata-Version: 2.4
Name: saini
Version: 1.0.5
Summary: Developer productivity toolkit: time tracking, Pomodoro timer, project tree visualization, and automation tools
Home-page: https://github.com/rohitsainier/saini
Author: Rohit Saini
Author-email: rohitsainier@gmail.com
Project-URL: Bug Reports, https://github.com/rohitsainier/saini/issues
Project-URL: Source, https://github.com/rohitsainier/saini
Project-URL: Documentation, https://github.com/rohitsainier/saini#readme
Keywords: git time-tracking pomodoro productivity developer-tools project-tree cli automation
Classifier: Development Status :: 4 - Beta
Classifier: Intended Audience :: Developers
Classifier: Topic :: Software Development
Classifier: Topic :: Software Development :: Version Control :: Git
Classifier: Topic :: Utilities
Classifier: License :: OSI Approved :: MIT License
Classifier: Programming Language :: Python :: 3
Classifier: Programming Language :: Python :: 3.7
Classifier: Programming Language :: Python :: 3.8
Classifier: Programming Language :: Python :: 3.9
Classifier: Programming Language :: Python :: 3.10
Classifier: Programming Language :: Python :: 3.11
Classifier: Programming Language :: Python :: 3.12
Classifier: Operating System :: OS Independent
Classifier: Environment :: Console
Requires-Python: >=3.7, <4
License-File: LICENSE
Requires-Dist: click>=8.0.0
Requires-Dist: rich>=10.0.0
Requires-Dist: gitpython>=3.1.0
Requires-Dist: pandas>=1.3.0
Requires-Dist: tabulate>=0.8.9
Provides-Extra: dev
Requires-Dist: pytest>=6.0; extra == "dev"
Requires-Dist: pytest-cov>=2.0; extra == "dev"
Requires-Dist: black>=22.0; extra == "dev"
Requires-Dist: flake8>=4.0; extra == "dev"
Requires-Dist: mypy>=0.950; extra == "dev"
Dynamic: author
Dynamic: author-email
Dynamic: classifier
Dynamic: description
Dynamic: description-content-type
Dynamic: home-page
Dynamic: keywords
Dynamic: license-file
Dynamic: project-url
Dynamic: provides-extra
Dynamic: requires-dist
Dynamic: requires-python
Dynamic: summary
